attotools/__init__.py
attotools/eqtype.py
attotools/io.py
attotools/test.py
attotools/toolfunctions.py
attotools/version.py
attotools/atstyles/__init__.py
attotools/atstyles/sci.mplstyle
attotools-0.0.5.dist-info/METADATA
attotools-0.0.5.dist-info/WHEEL
attotools-0.0.5.dist-info/top_level.txt
attotools-0.0.5.dist-info/RECORD
