Metadata-Version: 2.2
Name: attotools
Version: 0.0.5
Summary: a package for data processing
Author: Shellwe Wang
Author-email: shellwe.wang@gmail.com
Classifier: Programming Language :: Python :: 3
Classifier: License :: OSI Approved :: MIT License
Classifier: Operating System :: OS Independent
Requires-Python: >=3.8
